{
    "Name": "Elements",
	"Category": "Magic",
    "1": [
        "*Physical Elements",
        "*Physical Elements",
        "*Physical Elements",
        "*Physical Elements",
        "*Physical Elements",
        "*Physical Elements"
    ],
    "2": [
        "*Physical Elements",
        "*Physical Elements",
        "*Physical Elements",
        "*Physical Elements",
        "*Physical Elements",
        "*Physical Elements"
    ],
    "3": [
        "*Physical Elements",
        "*Physical Elements",
        "*Physical Elements",
        "*Physical Elements",
        "*Physical Elements",
        "*Physical Elements"
    ],
    "4": [
        "*Ethereal Elements",
        "*Ethereal Elements",
        "*Ethereal Elements",
        "*Ethereal Elements",
        "*Ethereal Elements",
        "*Ethereal Elements"
    ],
    "5": [
        "*Ethereal Elements",
        "*Ethereal Elements",
        "*Ethereal Elements",
        "*Ethereal Elements",
        "*Ethereal Elements",
        "*Ethereal Elements"
    ],
    "6": [
        "*Ethereal Elements",
        "*Ethereal Elements",
        "*Ethereal Elements",
        "*Ethereal Elements",
        "*Ethereal Elements",
        "*Ethereal Elements"
    ]
}